pytest_cairo/__init__.py
pytest_cairo/_version.py
pytest_cairo/context.py
pytest_cairo/contract.py
pytest_cairo/contract_index.py
pytest_cairo/fixture.py
pytest_cairo/function.py
pytest_cairo/helpers.cairo
pytest_cairo/info_collector.py
pytest_cairo/patch.py
pytest_cairo/plugin.py
pytest_cairo-0.1.0.dist-info/LICENSE
pytest_cairo-0.1.0.dist-info/METADATA
pytest_cairo-0.1.0.dist-info/WHEEL
pytest_cairo-0.1.0.dist-info/entry_points.txt
pytest_cairo-0.1.0.dist-info/top_level.txt
pytest_cairo-0.1.0.dist-info/RECORD
