Metadata-Version: 2.1
Name: pytest-cairo
Version: 0.1.0
Summary: Pytest support for cairo-lang and starknet
Home-page: https://github.com/TimNooren/pytest-cairo
License: UNKNOWN
Platform: UNKNOWN
Classifier: Framework :: Pytest
Requires-Python: >=3.7
License-File: LICENSE
Requires-Dist: cairo-lang (>=0.8.1)
Requires-Dist: pytest
